slakh_dataset/__init__.py
slakh_dataset/constants.py
slakh_dataset/data_classes.py
slakh_dataset/dataset.py
slakh_dataset/midi.py
slakh_dataset/splits/original.json
slakh_dataset/splits/pitch_bend_info.json
slakh_dataset/splits/problem_stems.json
slakh_dataset/splits/redux.json
slakh_dataset/splits/splits_v2.json
slakh_dataset-0.1.25.dist-info/LICENSE
slakh_dataset-0.1.25.dist-info/WHEEL
slakh_dataset-0.1.25.dist-info/METADATA
slakh_dataset-0.1.25.dist-info/RECORD
